LICENSE
README.md
setup.py
detector/__init__.py
detector/detector.py
openai_detector.egg-info/PKG-INFO
openai_detector.egg-info/SOURCES.txt
openai_detector.egg-info/dependency_links.txt
openai_detector.egg-info/requires.txt
openai_detector.egg-info/top_level.txt