Metadata-Version: 2.1
Name: openai-detector
Version: 0.1.1
Summary: Open AI classifier for indicating AI-written text
Home-page: https://github.com/promptslab/openai-detector
Author: monk1337
Maintainer: All our contributors
License: Apache
Platform: UNKNOWN
Requires-Python: >=3.7.0
License-File: LICENSE
